{
    "fluentMethods": true,
    "relationships": [
        {
            "relationshipType": "one-to-one",
            "relationshipValidateRules": "required",
            "relationshipName": "aluno",
            "otherEntityName": "aluno",
            "otherEntityField": "id",
            "ownerSide": true,
            "otherEntityRelationshipName": "doutorando"
        }
    ],
    "fields": [
        {
            "fieldName": "terminou1OPeriodo",
            "fieldType": "Boolean",
            "fieldValidateRules": [
                "required"
            ]
        }
    ],
    "changelogDate": "20161203141217",
    "entityTableName": "doutorando",
    "dto": "no",
    "pagination": "no",
    "service": "no"
}